README.rst
setup.py
proigia_logstash_formatter/__init__.py
proigia_logstash_formatter.egg-info/PKG-INFO
proigia_logstash_formatter.egg-info/SOURCES.txt
proigia_logstash_formatter.egg-info/dependency_links.txt
proigia_logstash_formatter.egg-info/not-zip-safe
proigia_logstash_formatter.egg-info/requires.txt
proigia_logstash_formatter.egg-info/top_level.txt