Metadata-Version: 1.1
Name: proigia-logstash-formatter
Version: 1.0
Summary: JSON formatter meant for logstash
Home-page: https://github.com/Proigia/proigia-logstash-formatter
Author: Wouter van Bommel
Author-email: wvanbommel@proigia.nl
License: MIT, see LICENSE file
Platform: UNKNOWN
Classifier: Development Status :: 5 - Production/Stable
Classifier: Intended Audience :: Developers
Classifier: License :: OSI Approved :: MIT License
Classifier: Natural Language :: English
Classifier: Programming Language :: Python
Classifier: Programming Language :: Python :: 3
